LICENSE
MANIFEST.in
README.rst
setup.py
django_simple_gmap.egg-info/PKG-INFO
django_simple_gmap.egg-info/SOURCES.txt
django_simple_gmap.egg-info/dependency_links.txt
django_simple_gmap.egg-info/top_level.txt
simple_gmap/__init__.py
simple_gmap/admin.py
simple_gmap/models.py
simple_gmap/tests.py
simple_gmap/views.py