Metadata-Version: 1.1
Name: django-simple-gmap
Version: 0.1
Summary: Simple Google Maps Integration For Django
Home-page: https://github.com/six519/django-simple-gmap
Author: Ferdinand Silva
Author-email: ferdinandsilva@ferdinandsilva.com
License: BSD License
Platform: UNKNOWN
Classifier: Environment :: Web Environment
Classifier: Framework :: Django
Classifier: Intended Audience :: Developers
Classifier: License :: OSI Approved :: BSD License
Classifier: Operating System :: OS Independent
Classifier: Programming Language :: Python
Classifier: Programming Language :: Python :: 2
Classifier: Programming Language :: Python :: 2.7
Classifier: Topic :: Internet :: WWW/HTTP
Classifier: Topic :: Internet :: WWW/HTTP :: Dynamic Content
